json5kit/__init__.py
json5kit/nodes.py
json5kit/visitor.py
json5kit-0.4.0.dist-info/LICENSE
json5kit-0.4.0.dist-info/METADATA
json5kit-0.4.0.dist-info/WHEEL
json5kit-0.4.0.dist-info/top_level.txt
json5kit-0.4.0.dist-info/RECORD
