Metadata-Version: 2.1
Name: json5kit
Version: 0.4.0
Summary: A Roundtrip parser and CST for JSON, JSONC and JSON5.
Home-page: https://github.com/tusharsadhwani/json5kit
Author: Tushar Sadhwani
Author-email: tushar.sadhwani000@gmail.com
License: MIT
Classifier: License :: OSI Approved :: MIT License
Classifier: Operating System :: OS Independent
Classifier: Programming Language :: Python :: 3
Classifier: Programming Language :: Python :: 3 :: Only
Classifier: Programming Language :: Python :: 3.7
Classifier: Programming Language :: Python :: 3.8
Classifier: Programming Language :: Python :: 3.9
Classifier: Programming Language :: Python :: 3.10
Classifier: Programming Language :: Python :: Implementation :: CPython
Classifier: Typing :: Typed
Requires-Python: >=3.7
License-File: LICENSE
Provides-Extra: dev
Requires-Dist: tox ; extra == 'dev'
Requires-Dist: black ; extra == 'dev'
Requires-Dist: mypy ; extra == 'dev'
Requires-Dist: pytest-cov ; extra == 'dev'
Requires-Dist: typing-extensions ; (python_version < "3.8") and extra == 'dev'
